MANIFEST.in
README.txt
quintagroup.dropdownmenu-configure.zcml
setup.cfg
setup.py
docs/CONTRIBUTORS.txt
docs/HISTORY.txt
docs/INSTALL.txt
docs/LICENSE.GPL
docs/LICENSE.txt
quintagroup/__init__.py
quintagroup.dropdownmenu.egg-info/PKG-INFO
quintagroup.dropdownmenu.egg-info/SOURCES.txt
quintagroup.dropdownmenu.egg-info/dependency_links.txt
quintagroup.dropdownmenu.egg-info/entry_points.txt
quintagroup.dropdownmenu.egg-info/namespace_packages.txt
quintagroup.dropdownmenu.egg-info/not-zip-safe
quintagroup.dropdownmenu.egg-info/requires.txt
quintagroup.dropdownmenu.egg-info/top_level.txt
quintagroup/dropdownmenu/TODO.txt
quintagroup/dropdownmenu/__init__.py
quintagroup/dropdownmenu/configure.zcml
quintagroup/dropdownmenu/interfaces.py
quintagroup/dropdownmenu/setuphandlers.py
quintagroup/dropdownmenu/util.py
quintagroup/dropdownmenu/Extensions/Install.py
quintagroup/dropdownmenu/browser/__init__.py
quintagroup/dropdownmenu/browser/configure.zcml
quintagroup/dropdownmenu/browser/controlpanel.py
quintagroup/dropdownmenu/browser/css.py
quintagroup/dropdownmenu/browser/menu.py
quintagroup/dropdownmenu/browser/viewlets.py
quintagroup/dropdownmenu/browser/resources/csshover.htc
quintagroup/dropdownmenu/browser/resources/drop_down.css
quintagroup/dropdownmenu/browser/resources/drop_down.js
quintagroup/dropdownmenu/browser/templates/sections.pt
quintagroup/dropdownmenu/browser/templates/sections_mobile.pt
quintagroup/dropdownmenu/browser/templates/sections_recurse.pt
quintagroup/dropdownmenu/profiles/default/browserlayer.xml
quintagroup/dropdownmenu/profiles/default/controlpanel.xml
quintagroup/dropdownmenu/profiles/default/cssregistry.xml
quintagroup/dropdownmenu/profiles/default/jsregistry.xml
quintagroup/dropdownmenu/profiles/default/metadata.xml
quintagroup/dropdownmenu/profiles/default/registry.xml
quintagroup/dropdownmenu/profiles/uninstall/cssregistry.xml
quintagroup/dropdownmenu/profiles/uninstall/quintagroup_dropdownmenu_uninstall.txt
quintagroup/dropdownmenu/tests/__init__.py
quintagroup/dropdownmenu/tests/base.py
quintagroup/dropdownmenu/tests/test_controlpanel.py
quintagroup/dropdownmenu/tests/test_docs.py
quintagroup/dropdownmenu/tests/test_installation.py