Metadata-Version: 1.0
Name: quintagroup.dropdownmenu
Version: 1.3.2
Summary: Multilevel portal dropdown menu for Plone sites.
Home-page: http://quintagroup.com/services/plone-development/products/quintagroup.dropdownmenu
Author: Quintagroup
Author-email: support@quintagroup.com
License: GPL
Keywords: web plone menu dropdown navigation
Platform: UNKNOWN
Classifier: Environment :: Web Environment
Classifier: Framework :: Zope2
Classifier: Framework :: Plone
Classifier: Framework :: Plone :: 3.2
Classifier: Framework :: Plone :: 3.3
Classifier: Framework :: Plone :: 4.0
Classifier: Framework :: Plone :: 4.1
Classifier: Framework :: Plone :: 4.2
Classifier: Framework :: Plone :: 4.3
Classifier: Programming Language :: Python
Classifier: Development Status :: 5 - Production/Stable
Classifier: Intended Audience :: Developers
Classifier: Natural Language :: English
Classifier: Operating System :: OS Independent
Classifier: Topic :: Internet :: WWW/HTTP :: Dynamic Content
Classifier: Topic :: Software Development :: Libraries :: Python Modules
Classifier: License :: OSI Approved :: GNU General Public License (GPL)
